tt_df/__init__.py
tt_df/pandas/__init__.py
tt_df/pandas/mock.py
tt_df-0.0.0a1.dist-info/licenses/LICENSE
tt_df-0.0.0a1.dist-info/METADATA
tt_df-0.0.0a1.dist-info/WHEEL
tt_df-0.0.0a1.dist-info/entry_points.txt
tt_df-0.0.0a1.dist-info/top_level.txt
tt_df-0.0.0a1.dist-info/RECORD
