Metadata-Version: 2.4
Name: tt-df
Version: 0.0.0a1
Summary: Test time tooling for dataframes.
Author: Carter Fendley
License: MIT License
Project-URL: Homepage, https://github.com/CarterFendley/test-time-dataframes
Classifier: Programming Language :: Python :: 3
Classifier: License :: OSI Approved :: MIT License
Classifier: Operating System :: OS Independent
License-File: LICENSE
Provides-Extra: dev
Requires-Dist: pytest; extra == "dev"
Requires-Dist: pytest-mock; extra == "dev"
Requires-Dist: pytest-cov; extra == "dev"
Requires-Dist: pre-commit; extra == "dev"
Requires-Dist: ruff; extra == "dev"
Provides-Extra: pandas
Requires-Dist: pandas; extra == "pandas"
Requires-Dist: pyarrow; extra == "pandas"
Dynamic: license-file
